{
  "$schema": "http://json-schema.org/draft-07/schema#",
  "$id": "https://scvs.owasp.org/bmm-profile-0.1.schema.json",
  "type": "object",
  "title": "OWASP SCVS BOM Maturity Model - Profile Schema",
  "$comment": "OWASP SCVS BOM Maturity Model schemas are published under the terms of the Apache License 2.0.",
  "required": [
    "profile"
  ],
  "properties": {
    "$schema": {"type": "string"},
    "profile": {"$ref": "#/definitions/profile_type"}
  },
  "definitions": {
    "identifiers_type": {
      "type": "array",
      "minItems": 0,
      "items": {"type": "string"}
    },
    "elements_type": {
      "type": "array",
      "minItems": 0,
      "items": {
        "type": "object",
        "properties": {
          "identifiers": {"$ref": "#/definitions/identifiers_type"},
          "weight": {"type": "number"},
          "required": {"type": "boolean"}
        },
        "required": [
          "identifiers",
          "weight",
          "required"
        ]
      }
    },
    "profile_type": {
      "type": "object",
      "properties": {
        "name": {"type": "string"},
        "version": {"type": "string"},
        "description": {"type": "string"},
        "creator": {"type": "string"},
        "elements": {"$ref": "#/definitions/elements_type"}
      },
      "required": [
        "name",
        "version",
        "elements"
      ]
    }
  }
}