{
  "profile": {
    "name": "Example profile",
    "version": "1.0",
    "description": "",
    "creator": "",
    "elements": [
      {
        "identifiers": [
          "urn:owasp:scvs:bmm:inventory:identifiers:name",
          "urn:owasp:scvs:bmm:inventory:identifiers:version"
        ],
        "weight": 1.0,
        "required": true
      },
      {
        "identifiers": [
          "urn:owasp:scvs:bmm:inventory:identifiers:cpe",
          "urn:owasp:scvs:bmm:inventory:identifiers:purl"
        ],
        "weight": 0.7,
        "required": false
      }
    ]
  }
}